oppositescore/__init__.py
oppositescore/evaluation/__init__.py
oppositescore/evaluation/dichotomyInferencer.py
oppositescore/evaluation/evaluation.py
oppositescore/evaluation/outdated_evaluation_angle.py
oppositescore/model/__init__.py
oppositescore/model/angle.py
oppositescore/model/base.py
oppositescore/model/dichotomye.py
oppositescore/trainer/__init__.py
oppositescore/trainer/angle_trainer.py
oppositescore/trainer/dichotomy_dataset.py
oppositescore/trainer/dichotomye_trainer.py
oppositescore/trainer/loss.py
oppositescore/utils/__init__.py
oppositescore/utils/utils.py
opposite_score-0.0.3.dist-info/METADATA
opposite_score-0.0.3.dist-info/WHEEL
opposite_score-0.0.3.dist-info/top_level.txt
opposite_score-0.0.3.dist-info/RECORD
