Metadata-Version: 2.4
Name: opposite-score
Version: 0.0.3
Summary: Optimized Text Embeddings Designed for Measuring Opposite/Contrasting Relationships
Home-page: https://github.com/cui-shaobo/conditional-dichotomy-quantification
Author: Shaobo Cui
Author-email: shaobo.cui@epfl.ch
Keywords: text embedding,NLP,opposite relationships,dichotomy
Classifier: Development Status :: 4 - Beta
Classifier: Intended Audience :: Developers
Classifier: License :: OSI Approved :: MIT License
Classifier: Programming Language :: Python :: 3.9
Requires-Python: >=3.7, <3.12
Requires-Dist: bitsandbytes
Requires-Dist: datasets
Requires-Dist: peft==0.15.2
Requires-Dist: boltons
Requires-Dist: scikit-learn
Requires-Dist: tqdm
Requires-Dist: huggingface-hub
Requires-Dist: scipy>=1.13.0
Requires-Dist: spacy>=3.7.6
Requires-Dist: tokenizers>=0.13.3
Requires-Dist: torch>=2.0.1
Requires-Dist: torchvision>=0.15.2
Requires-Dist: transformers>=4.31.0
Dynamic: author
Dynamic: author-email
Dynamic: classifier
Dynamic: description
Dynamic: description-content-type
Dynamic: home-page
Dynamic: keywords
Dynamic: requires-dist
Dynamic: requires-python
Dynamic: summary
